AUTHORS.rst
CONTRIBUTING.rst
HISTORY.rst
LICENSE
MANIFEST.in
README.rst
setup.cfg
setup.py
docs/Makefile
docs/authors.rst
docs/conf.py
docs/contributing.rst
docs/history.rst
docs/index.rst
docs/make.bat
docs/modules.rst
docs/pronouncing.rst
docs/tutorial.rst
pronouncing/__init__.py
pronouncing/cmudict-0.7b
pronouncing.egg-info/PKG-INFO
pronouncing.egg-info/SOURCES.txt
pronouncing.egg-info/dependency_links.txt
pronouncing.egg-info/top_level.txt
pronouncing.egg-info/zip-safe
tests/__init__.py
tests/test_pronouncing.py